DeepMTP/__init__.py
DeepMTP/branch_models.py
DeepMTP/dataset.py
DeepMTP/hpo_worker.py
DeepMTP/main.py
DeepMTP/main_streamlit.py
DeepMTP/random_search.py
DeepMTP/random_search_streamlit.py
DeepMTP/simple_hyperband.py
DeepMTP/simple_hyperband_streamlit.py
DeepMTP/tests/__init__.py
DeepMTP/tests/test_branch_models.py
DeepMTP/tests/test_data_utils.py
DeepMTP/tests/test_dataset.py
DeepMTP/tests/test_eval_utils.py
DeepMTP/tests/test_hpo_worker.py
DeepMTP/tests/test_main.py
DeepMTP/tests/test_model_utils.py
DeepMTP/tests/test_random_search.py
DeepMTP/tests/test_simple_hyperband.py
DeepMTP/tests/test_utils.py
DeepMTP/utils/__init__.py
DeepMTP/utils/data_utils.py
DeepMTP/utils/eval_utils.py
DeepMTP/utils/model_utils.py
DeepMTP/utils/tests.py
DeepMTP/utils/utils.py
DeepMTP-0.0.22.dist-info/LICENSE.md
DeepMTP-0.0.22.dist-info/METADATA
DeepMTP-0.0.22.dist-info/WHEEL
DeepMTP-0.0.22.dist-info/top_level.txt
DeepMTP-0.0.22.dist-info/RECORD
