Metadata-Version: 2.1
Name: DeepMTP
Version: 0.0.22
Summary: a Deep Learning Framework for Multi-target Prediction
Home-page: https://github.com/diliadis/DeepMTP
Author: Dimitris Iliadis
Author-email: dimitrios.iliadis@ugent.be
License: MIT
Classifier: Intended Audience :: Education
Classifier: License :: OSI Approved :: MIT License
Classifier: Programming Language :: Python :: 3
Requires-Python: >=3.7
License-File: LICENSE.md
Requires-Dist: liac-arff
Requires-Dist: matplotlib
Requires-Dist: matplotlib-inline
Requires-Dist: more-itertools
Requires-Dist: numpy
Requires-Dist: pandas
Requires-Dist: pillow
Requires-Dist: prettytable
Requires-Dist: scikit-learn
Requires-Dist: scikit-multilearn
Requires-Dist: scipy
Requires-Dist: wandb
Requires-Dist: wget
Requires-Dist: tensorboard
Requires-Dist: streamlit
Requires-Dist: tqdm
